{"specversion":"1.0","id":"215bb5a5-0e1b-4841-bb04-8d8d9fa51b4c","source":"https://example.com/change_request.do?sysparm_query=number=CHG0030003","type":"com.ibm.sdlc.snow.changerequest.discovered","datacontenttype":"application/json","time":"2024-10-03T19:44:36.217581027Z","structuredcontentmode":"true","responsetime":"0","connectionid":"16d2aa2e-6945-4a6c-a95e-fc8a46b4f65e","componentname":"connector","tooltype":"com.ibm.sdlc.type.snow","data":{"end_date":"","connectionmode":"live","short_description":"Server backup is required","reason":"null","work_start":"","close_code":"null","delivery_task":"","instance":"example.com","backout_plan":"","description":"","calendar_duration":"","type":"Normal","close_notes":"","sys_id":"fdf149995301121040565eb0a0490e19","number":"CHG0030003","test_plan":"","contact_type":"null","sys_domain":"global","state":"New","justification":"","raw_data":{"parent":"","reason":null,"watch_list":"","upon_reject":"Cancel all future Tasks","sys_updated_on":"2024-10-03 12:42:22","type":"Normal","approval_history":"","number":"CHG0030003","test_plan":"","cab_delegate":"","requested_by_date":"","state":"New","sys_created_by":"abel.tuter","knowledge":"false","order":"","phase":"Requested","cmdb_ci":"","delivery_plan":"","contract":"","impact":"3 - Low","active":"true","work_notes_list":"","priority":"4 - Low","sys_domain_path":"/","cab_recommendation":"","production_system":"false","review_date":"","business_duration":"","group_list":"","requested_by":"Abel Tuter","change_plan":"","approval_set":"","copied_from":"","implementation_plan":"","universal_request":"","end_date":"","short_description":"Server backup is required","correlation_display":"","delivery_task":"","work_start":"","additional_assignee_list":"","outside_maintenance_schedule":"false","std_change_producer_version":"","service_offering":"","sys_class_name":"Change Request","closed_by":"","follow_up":"","reassignment_count":"0","review_status":"","assigned_to":"","start_date":"","sla_due":"UNKNOWN","comments_and_work_notes":"","escalation":"Normal","upon_approval":"Proceed to Next Task","correlation_id":"","made_sla":"true","backout_plan":"","conflict_status":"Not Run","task_effective_number":"CHG0030003","sys_updated_by":"abel.tuter","opened_by":"Abel Tuter","user_input":"","sys_created_on":"2024-10-03 12:42:22","on_hold_task":"","sys_domain":"global","route_reason":"","closed_at":"","review_comments":"","business_service":"","time_worked":"","chg_model":"Normal","expected_start":"","opened_at":"2024-10-03 12:42:14","work_end":"","phase_state":"Open","work_notes":"","close_code":null,"assignment_group":"","description":"","on_hold_reason":"","calendar_duration":"","close_notes":"","sys_id":"fdf149995301121040565eb0a0490e19","contact_type":null,"cab_required":"false","urgency":"3 - Low","scope":"Medium","company":"","justification":"","activity_due":"UNKNOWN","comments":"","approval":"Not Yet Requested","due_date":"","sys_mod_count":"0","on_hold":"false","sys_tags":"","cab_date_time":"","conflict_last_run":"","unauthorized":"false","location":"","risk":"Moderate","category":"Other","risk_impact_analysis":""},"sys_created_by":"abel.tuter","assigned_to":"","start_date":"","cmdb_ci":"","approval":"Not Yet Requested","impact":"3 - Low","work_notes_list":"","business_service":"","priority":"4 - Low","production_system":"false","work_end":"","connection_id":"16d2aa2e-6945-4a6c-a95e-fc8a46b4f65e","category":"Other","work_notes":[""],"implementation_plan":""}}
